stackoverflow_to_sqlite/__init__.py
stackoverflow_to_sqlite/cli.py
stackoverflow_to_sqlite/sqlite_helpers.py
stackoverflow_to_sqlite/stack_exchange_api.py
stackoverflow_to_sqlite/types.py
stackoverflow_to_sqlite-0.1.1.dist-info/entry_points.txt
stackoverflow_to_sqlite-0.1.1.dist-info/LICENSE
stackoverflow_to_sqlite-0.1.1.dist-info/WHEEL
stackoverflow_to_sqlite-0.1.1.dist-info/METADATA
stackoverflow_to_sqlite-0.1.1.dist-info/RECORD
