Metadata-Version: 2.1
Name: stackoverflow-to-sqlite
Version: 0.1.1
Summary: Quickly and painlessly dump all your Airtable schemas & data to JSON.
Keywords: stackoverflow,backup,exporter,sqlite
Author-email: David Brownman <beamneocube@gmail.com>
Requires-Python: >=3.12
Classifier: Programming Language :: Python :: 3
Classifier: Development Status :: 4 - Beta
Classifier: Environment :: Console
Classifier: License :: OSI Approved :: MIT License
Classifier: Operating System :: OS Independent
Classifier: Topic :: System :: Archiving :: Backup
Requires-Dist: click==8.1.3
Requires-Dist: httpx==0.27.0
Requires-Dist: sqlite-utils==3.36
Requires-Dist: pyright==1.1.364 ; extra == "ci"
Requires-Dist: ruff==0.4.5 ; extra == "ci"
Requires-Dist: twine==4.0.2 ; extra == "release"
Requires-Dist: build==0.10.0 ; extra == "release"
Requires-Dist: pytest==8.2.1 ; extra == "test"
Requires-Dist: pytest-httpx==0.30.0 ; extra == "test"
Project-URL: Author, https://xavd.id
Project-URL: Bug Tracker, https://github.com/xavdid/stackoverflow-to-sqlite/issues
Project-URL: Changelog, https://github.com/xavdid/stackoverflow-to-sqlite/blob/main/CHANGELOG.md
Project-URL: Homepage, https://github.com/xavdid/stackoverflow-to-sqlite
Provides-Extra: ci
Provides-Extra: release
Provides-Extra: test
